rjsonc-0.1.2.dist-info/METADATA
rjsonc-0.1.2.dist-info/WHEEL
rjsonc-0.1.2.dist-info/licenses/LICENSE
rjsonc/__init__.py
rjsonc/py.typed
rjsonc/rjsonc.cpython-310-powerpc64le-linux-gnu.so
rjsonc/rjsonc.pyi
rjsonc/wrapper.py
rjsonc-0.1.2.dist-info/RECORD
