Metadata-Version: 2.4
Name: rjsonc
Version: 0.1.2
Classifier: Programming Language :: Rust
Classifier: Programming Language :: Python :: Implementation :: CPython
Classifier: Programming Language :: Python :: Implementation :: PyPy
Requires-Dist: pytest ; extra == 'tests'
Provides-Extra: tests
License-File: LICENSE
Summary: Load JSON with comments. Fast.
Keywords: json,comments,comment,json-comment,json-comments
Author-email: AWeirdDev <awdjared@gmail.com>
Requires-Python: >=3.8
